{"cameraMode":{"drawMode":0,"name":"Shaded","section":"Shading Mode"},"sceneLighting":false,"audioPlay":false,"sceneViewState":{"m_AlwaysRefresh":false,"showFog":true,"showSkybox":false,"showFlares":true,"showImageEffects":true,"showParticleSystems":true,"showVisualEffectGraphs":true,"m_FxEnabled":true},"in2DMode":false,"pivot":{"x":-1.5790741443634034,"y":3.370346784591675,"z":7.6188554763793949},"rotation":{"x":-0.22766447067260743,"y":0.03270849958062172,"z":-0.007650954648852348,"w":-0.9731643795967102},"size":16.031190872192384,"orthographic":false}